disnake/ext/icallbacks/__init__.py
disnake/ext/icallbacks/callback.py
disnake/ext/icallbacks/extension.py
disnake/ext/icallbacks/manager.py
disnake/ext/icallbacks/utils.py
disnake_ext_icallbacks-1.0.0.dist-info/LICENSE
disnake_ext_icallbacks-1.0.0.dist-info/METADATA
disnake_ext_icallbacks-1.0.0.dist-info/WHEEL
disnake_ext_icallbacks-1.0.0.dist-info/top_level.txt
disnake_ext_icallbacks-1.0.0.dist-info/RECORD
